zswag/__init__.py
zswag/app.py
zswag/doc.py
zswag/gen.py
zswag/reflect.py
zswag/test/calc/__init__.py
zswag/test/calc/__main__.py
zswag/test/calc/api.yaml
zswag/test/calc/calculator.zs
zswag/test/calc/client.py
zswag/test/calc/server.py
zswag-1.9.1.dist-info/licenses/LICENSE
zswag-1.9.1.dist-info/METADATA
zswag-1.9.1.dist-info/WHEEL
zswag-1.9.1.dist-info/top_level.txt
zswag-1.9.1.dist-info/RECORD
