Metadata-Version: 2.4
Name: zswag
Version: 1.9.1
Summary: OpenAPI service transport layer for zserio.
Home-page: https://github.com/klebert-engineering/zswag
Author: Klebert Engineering
Author-email: team@klebert-engineering.de
License: BSD-3 Clause
Classifier: Programming Language :: Python :: 3
Classifier: Operating System :: OS Independent
Classifier: License :: OSI Approved :: BSD License
Requires-Python: >=3.10
License-File: LICENSE
Requires-Dist: pyzswagcl==1.9.1
Requires-Dist: connexion~=2.14.2
Requires-Dist: requests
Requires-Dist: zserio<3.0.0
Requires-Dist: pyyaml
Requires-Dist: openapi-spec-validator
Dynamic: author
Dynamic: author-email
Dynamic: classifier
Dynamic: description
Dynamic: description-content-type
Dynamic: home-page
Dynamic: license
Dynamic: license-file
Dynamic: requires-dist
Dynamic: requires-python
Dynamic: summary
